{
  "meta": {
    "source": "DMI HARMONIE",
    "updatedAt": "2026-03-31 23:51 UTC",
    "location": "TASIILAQ",
    "model": "harmonie_ig_sf",
    "forecastInfo": "Latest available forecast step",
    "instanceId": "2026-03-31T210000Z",
    "lastSuccessfulUpdate": "2026-03-31 23:51 UTC",
    "lastAttemptFailed": null,
    "stale": false
  },
  "inputs": {
    "icePressure": 1006.5,
    "seaPressure": 1003.8,
    "gradient": 2.7,
    "d6": -5.9,
    "d12": 0.6,
    "seaPressureDelta6h": 6.2,
    "seaPressureDelta12h": 8.6,
    "sf6": 0.0,
    "sf12": 0.0,
    "pressureFallAcceleration": 0.0,
    "iceWind": 11.3,
    "iceWindTrend6h": 4.8,
    "coastIceDeltaT": 38.5,
    "iceTempTrend24h": -5.6,
    "iceTempTrend72h": -13.5,
    "ventilIndex": 0.0,
    "ventilD6": -3.6,
    "ventilD12": -0.5,
    "coastSeaPressure": 1006.4,
    "coastGate": 0.2,
    "coastGateD6": -6.0,
    "coastGateD12": -1.3
  },
  "scores": {
    "reservoir": 39,
    "trigger": 5,
    "coupling": 13,
    "potential": 14,
    "risk": 34
  },
  "derived": {
    "watch": false,
    "isLadning": false,
    "sector": "E2",
    "cycloneInTriggerZone": true,
    "cycloneScore": 18,
    "piteraqMismatch": false,
    "usedInstanceIds": [
      "2026-03-31T210000Z"
    ],
    "fetchErrors": {},
    "seaMinLon": -27.5,
    "seaMinLat": 66.4,
    "seaCentroidPressure": 1006.5,
    "seaCentroidLon": -30.864,
    "seaCentroidLat": 64.956,
    "seaCentroidSector": "C2",
    "seaMinCentroidSpread": 2.7,
    "seaMinMotionKm6": 0.0,
    "westMeanPressure": 1007.3,
    "midMeanPressure": 1009.0,
    "eastMeanPressure": 1004.8,
    "coastSeaPressure": 1006.4,
    "gateMid": -1.7,
    "gateEast": 2.5,
    "ventilIndex": 0.0,
    "ventilD6": -3.6,
    "ventilD12": -0.5,
    "coastGate": 0.2,
    "coastGateD6": -6.0,
    "coastGateD12": -1.3,
    "icePressureAnomNow": -6.7,
    "icePressureAnom72hMean": -8.2,
    "icePressureTrend24h": 7.7,
    "icePressureTrend72h": 10.0,
    "coldSupport72h": 36.7,
    "katabaticPotential": 59,
    "seaLowDepth": 0.0,
    "gradientBoost": 0.0,
    "accG": -12.4,
    "accS": 0.0,
    "earlier6hFall": 0.0,
    "pressureFallAcceleration": 0.0,
    "potentialRaw": 23,
    "potentialReservoirFactor": 0.6,
    "lpBearingFromSea": 225.4,
    "lpPreviousBearingFromSea": 224.6,
    "lpBearingDistanceToNorth": 134.6,
    "lpBearingTrend6h": 0.7,
    "lpTrendLabel": "LPV+1W",
    "lpMotionBearing6h": 227.5,
    "lpMotionCardinal6h": "W",
    "lpApproachSpeedDeg6h": 0.7,
    "lpApproachingFavoredSector": false,
    "lpDistanceToFavoredSector": 74.6,
    "lpDistanceScore": 0,
    "lpSectorScore": 20,
    "lpGeometryScore": 24,
    "lpGeometryGate": 0.15,
    "lpAlignmentLabel": "south",
    "sustainedPiteraqScore": 14,
    "sustainedPiteraqStage": "none",
    "sustainedPiteraqNearHits": 0,
    "sustainedPiteraqStrongHits": 0,
    "katabaticLoadingScore": 70,
    "katabaticLoadingStage": "loading",
    "katabaticColdHits24h": 3,
    "katabaticDeepColdHits24h": 2,
    "katabaticReadinessLevel": "LOADED",
    "katabaticReadinessColor": "ORG",
    "piteraqHazardLevel": "GRN",
    "lpOffsetHpa": -2.7,
    "lpDistanceKm": 222.5,
    "accUncertain": false,
    "trendDataStatus": "ok",
    "qualityFlags": [
      "cold_reservoir_building_24h",
      "cold_reservoir_building_72h",
      "katabatic_loading",
      "sea_field_spread_moderate"
    ],
    "selectedTimes": {
      "now": {
        "validTime": "2026-04-01T00:00:00.000Z",
        "diffHours": 0.15
      },
      "h6_from_history": "2026-03-31T17:00:00Z",
      "h12_from_history": "2026-03-31T12:00:00Z",
      "h24_from_history": "2026-03-31T00:00:00Z",
      "h72_from_history": "2026-03-28T23:00:00Z"
    },
    "usedIcePressurePoints": 3,
    "usedIceTempPoints": 3,
    "usedIceWindPoints": 3,
    "usedSeaPressurePoints": 10,
    "usedSeaTempPoints": 12
  },
  "output": {
    "level": "GRN",
    "phase": "PITERAQ LOW",
    "message": "GRN34 LOADLOADED PITGRN H24-48T RES39 TRG5 CPL13 GR2.7 LPV+1W LPD75 VG0 CG0"
  }
}