{
  "updatedAt": "2026-03-19 21:00 UTC",
  "location": "TASIILAQ",
  "model": "harmonie_ig_sf",
  "instanceId": "2026-03-19T180000Z",
  "lastSuccessfulUpdate": "2026-03-19 21:00 UTC",
  "forecastInfo": "Latest available forecast step",
  "stale": false,
  "level": "GRN",
  "phase": "PITERAQ LOW",
  "risk": 32,
  "watch": false,
  "message": "GRN32 12-24T RES20 TRG51 CPL63 ICE999 SEA974 GR25.0 AG11 SF63.0 LPB225 LPV+34E LPD75 LPG36 VG6 CG22 CT24-16",
  "trendDataStatus": "ok",
  "qualityFlags": [
    "cold_reservoir_building_24h",
    "lp_approaching_favored_sector",
    "sea_field_spread_moderate",
    "sea_min_motion_high"
  ],
  "reservoir": 20,
  "trigger": 51,
  "coupling": 63,
  "icePressure": 998.6,
  "seaPressure": 973.7,
  "gradient": 25.0,
  "sf6": 3.0,
  "accG": 11.1,
  "regionalZone": "M3",
  "lpBearing": 224.8,
  "lpBearingTrend6h": 34.1,
  "lpTrendLabel": "LPV+34E",
  "lpDistanceToFavoredSector": 75.2,
  "lpDistanceScore": 0,
  "lpGeometryScore": 36,
  "lpApproachSpeedDeg6h": 34.1,
  "lpSectorScore": 20,
  "lpApproachingFavoredSector": true
}